odoo/addons/fieldservice_stage_server_action/README.rst
odoo/addons/fieldservice_stage_server_action/__init__.py
odoo/addons/fieldservice_stage_server_action/__manifest__.py
odoo/addons/fieldservice_stage_server_action/data/base_automation.xml
odoo/addons/fieldservice_stage_server_action/data/fsm_stage.xml
odoo/addons/fieldservice_stage_server_action/data/ir_server_action.xml
odoo/addons/fieldservice_stage_server_action/i18n/de.po
odoo/addons/fieldservice_stage_server_action/i18n/es.po
odoo/addons/fieldservice_stage_server_action/i18n/es_AR.po
odoo/addons/fieldservice_stage_server_action/i18n/es_CL.po
odoo/addons/fieldservice_stage_server_action/i18n/fieldservice_stage_server_action.pot
odoo/addons/fieldservice_stage_server_action/i18n/it.po
odoo/addons/fieldservice_stage_server_action/i18n/pt_BR.po
odoo/addons/fieldservice_stage_server_action/models/__init__.py
odoo/addons/fieldservice_stage_server_action/models/fsm_equipment.py
odoo/addons/fieldservice_stage_server_action/models/fsm_location.py
odoo/addons/fieldservice_stage_server_action/models/fsm_order.py
odoo/addons/fieldservice_stage_server_action/models/fsm_person.py
odoo/addons/fieldservice_stage_server_action/models/fsm_stage.py
odoo/addons/fieldservice_stage_server_action/readme/CONFIGURE.rst
odoo/addons/fieldservice_stage_server_action/readme/CONTRIBUTORS.rst
odoo/addons/fieldservice_stage_server_action/readme/DESCRIPTION.rst
odoo/addons/fieldservice_stage_server_action/readme/USAGE.rst
odoo/addons/fieldservice_stage_server_action/static/description/icon.png
odoo/addons/fieldservice_stage_server_action/static/description/index.html
odoo/addons/fieldservice_stage_server_action/tests/__init__.py
odoo/addons/fieldservice_stage_server_action/tests/test_fsm_stage.py
odoo/addons/fieldservice_stage_server_action/views/fsm_stage.xml
odoo14_addon_fieldservice_stage_server_action-14.0.1.0.2.dist-info/METADATA
odoo14_addon_fieldservice_stage_server_action-14.0.1.0.2.dist-info/WHEEL
odoo14_addon_fieldservice_stage_server_action-14.0.1.0.2.dist-info/top_level.txt
odoo14_addon_fieldservice_stage_server_action-14.0.1.0.2.dist-info/RECORD
